pyodmongo/__init__.py
pyodmongo/version.py
pyodmongo/engines/engines.py
pyodmongo/engines/utils.py
pyodmongo/models/db_decimal.py
pyodmongo/models/db_field_info.py
pyodmongo/models/db_model.py
pyodmongo/models/fields.py
pyodmongo/models/id_model.py
pyodmongo/models/metaclasses.py
pyodmongo/models/paginate.py
pyodmongo/models/query_operators.py
pyodmongo/models/responses.py
pyodmongo/models/sort_operators.py
pyodmongo/queries/__init__.py
pyodmongo/queries/operators.py
pyodmongo/queries/query_string.py
pyodmongo/services/aggregate_stages.py
pyodmongo/services/model_init.py
pyodmongo/services/reference_pipeline.py
pyodmongo/services/verify_subclasses.py
pyodmongo-1.7.0.dist-info/METADATA
pyodmongo-1.7.0.dist-info/WHEEL
pyodmongo-1.7.0.dist-info/licenses/LICENSE
pyodmongo-1.7.0.dist-info/RECORD
